artella/__init__.py
artella/plugins/__init__.py
artella/plugins/getdependencies/__init__.py
artella/plugins/getdependencies/__version__.py
artella/plugins/getdependencies/_version.py
artella/plugins/getdependencies/artella-plugin.json
artella/plugins/getdependencies/getdependencies.py
artella/plugins/getdependencies/maya/__init__.py
artella/plugins/getdependencies/maya/getdependencies.py
artella/plugins/getdependencies/resources/getdependencies.png
artella/plugins/getdependencies/widgets/__init__.py
artella/plugins/getdependencies/widgets/listdialog.py
artella/plugins/getdependencies/widgets/outputdialog.py
tests/__init__.py
tests/test_plugin.py
artella_plugins_getdependencies-1.0.10.dist-info/METADATA
artella_plugins_getdependencies-1.0.10.dist-info/WHEEL
artella_plugins_getdependencies-1.0.10.dist-info/top_level.txt
artella_plugins_getdependencies-1.0.10.dist-info/RECORD
