Metadata-Version: 2.1
Name: artella-plugins-getdependencies
Version: 1.0.10
Summary: Artella Plugin that allows to recursively download all dependencies of a DCC file.
Home-page: https://github.com/artella/artella-plugins-getdependencies
Author: Artella, Inc
Author-email: support@artella.com
License: UNKNOWN
Platform: UNKNOWN
Requires-Dist: artella-plugins-core
Provides-Extra: dev
Requires-Dist: wheel ; extra == 'dev'
Provides-Extra: test
Requires-Dist: pytest ; extra == 'test'
